{
  "id": "chat-gui-probe-channel",
  "name": "chat-gui-probe-channel",
  "title": "Chat GUI 无头测试通道（文件监听 probe）",
  "description": "",
  "status": "in_progress",
  "dev_type": null,
  "scope": null,
  "package": null,
  "priority": "P2",
  "creator": "wangmen",
  "assignee": "wangmen",
  "createdAt": "2026-07-03",
  "completedAt": null,
  "branch": null,
  "base_branch": "main",
  "worktree_path": null,
  "commit": null,
  "pr_url": null,
  "subtasks": [],
  "children": [],
  "parent": null,
  "relatedFiles": [],
  "notes": "",
  "meta": {}
}